plone.app.caching-4.1.1-py3.13-nspkg.pth
plone/app/caching/__init__.py
plone/app/caching/caching.zcml
plone/app/caching/configure.zcml
plone/app/caching/interfaces.py
plone/app/caching/lastmodified.py
plone/app/caching/lookup.py
plone/app/caching/profiles.zcml
plone/app/caching/purge.py
plone/app/caching/setuphandlers.py
plone/app/caching/testing.py
plone/app/caching/utils.py
plone/app/caching/browser/__init__.py
plone/app/caching/browser/configure.zcml
plone/app/caching/browser/controlpanel.pt
plone/app/caching/browser/controlpanel.py
plone/app/caching/browser/edit.pt
plone/app/caching/browser/edit.py
plone/app/caching/browser/import.pt
plone/app/caching/browser/plone.app.caching.gif
plone/app/caching/browser/purge.pt
plone/app/caching/browser/ramcache.pt
plone/app/caching/operations/__init__.py
plone/app/caching/operations/configure.zcml
plone/app/caching/operations/default.py
plone/app/caching/operations/etags.py
plone/app/caching/operations/ramcache.py
plone/app/caching/operations/utils.py
plone/app/caching/profiles/default/controlpanel.xml
plone/app/caching/profiles/default/metadata.xml
plone/app/caching/profiles/default/registry/basesettings.xml
plone/app/caching/profiles/default/registry/generic.xml
plone/app/caching/profiles/default/registry/moderate.xml
plone/app/caching/profiles/default/registry/strong.xml
plone/app/caching/profiles/default/registry/terse.xml
plone/app/caching/profiles/default/registry/weak.xml
plone/app/caching/profiles/uninstall/controlpanel.xml
plone/app/caching/profiles/uninstall/registry/basesettings.xml
plone/app/caching/profiles/uninstall/registry/moderate.xml
plone/app/caching/profiles/uninstall/registry/strong.xml
plone/app/caching/profiles/uninstall/registry/terse.xml
plone/app/caching/profiles/uninstall/registry/weak.xml
plone/app/caching/profiles/v2/registry/terse.xml
plone/app/caching/profiles/with-caching-proxy/registry.xml
plone/app/caching/profiles/without-caching-proxy/registry.xml
plone/app/caching/tests/__init__.py
plone_app_caching-4.1.1.dist-info/METADATA
plone_app_caching-4.1.1.dist-info/WHEEL
plone_app_caching-4.1.1.dist-info/entry_points.txt
plone_app_caching-4.1.1.dist-info/namespace_packages.txt
plone_app_caching-4.1.1.dist-info/top_level.txt
plone_app_caching-4.1.1.dist-info/RECORD
