Metadata-Version: 2.2
Name: plone.app.caching
Version: 4.1.1
Summary: Plone UI and default rules for plone.caching/z3c.caching
Home-page: https://github.com/plone/plone.app.caching
Author: Plone Foundation
Author-email: plone-developers@lists.sourceforge.net
License: GPL version 2
Keywords: plone caching
Classifier: Development Status :: 5 - Production/Stable
Classifier: Environment :: Web Environment
Classifier: Framework :: Plone
Classifier: Framework :: Plone :: 6.0
Classifier: Framework :: Plone :: Core
Classifier: Framework :: Zope :: 5
Classifier: License :: OSI Approved :: GNU General Public License v2 (GPLv2)
Classifier: Operating System :: OS Independent
Classifier: Programming Language :: Python
Classifier: Programming Language :: Python :: 3.8
Classifier: Programming Language :: Python :: 3.9
Classifier: Programming Language :: Python :: 3.10
Classifier: Programming Language :: Python :: 3.11
Requires-Python: >=3.8
Requires-Dist: Products.CMFCore
Requires-Dist: Products.CMFDynamicViewFTI
Requires-Dist: Products.CMFPlone
Requires-Dist: Products.GenericSetup
Requires-Dist: Products.statusmessages
Requires-Dist: Zope
Requires-Dist: setuptools
Requires-Dist: python-dateutil
Requires-Dist: plone.app.registry
Requires-Dist: plone.base
Requires-Dist: plone.caching
Requires-Dist: plone.dexterity
Requires-Dist: plone.cachepurging
Requires-Dist: plone.memoize
Requires-Dist: plone.namedfile
Requires-Dist: plone.protect
Requires-Dist: plone.registry
Requires-Dist: plone.transformchain
Requires-Dist: plone.z3cform
Requires-Dist: z3c.caching
Requires-Dist: z3c.form
Requires-Dist: z3c.zcmlhook
Requires-Dist: zope.ramcache
Provides-Extra: test
Requires-Dist: persistent; extra == "test"
Requires-Dist: plone.app.contenttypes[test]; extra == "test"
Requires-Dist: plone.app.testing; extra == "test"
Requires-Dist: plone.app.textfield; extra == "test"
Requires-Dist: plone.behavior; extra == "test"
Requires-Dist: plone.testing; extra == "test"
Requires-Dist: pytz; extra == "test"
Requires-Dist: transaction; extra == "test"
Dynamic: author
Dynamic: author-email
Dynamic: classifier
Dynamic: description
Dynamic: description-content-type
Dynamic: home-page
Dynamic: keywords
Dynamic: license
Dynamic: provides-extra
Dynamic: requires-dist
Dynamic: requires-python
Dynamic: summary
